conv.v
`include "IFMD_ram.v"
module conv(
    input wire clk,
    input wire conv_start,

    input wire [7:0] IFMD_out,
    output reg IFMD_read,
    output reg [5:0] read_addr,

    //output reg[15:0] OFMD_in,
    output reg [5:0]OFMD_addr,
    output reg conv_done
);

    //mac
    reg [15:0] mult [0:8];
    //reg [15:0] result [0:35];
    reg [13:0] mult8_reg;
    reg [15:0] sum1 [0:3];
    reg [15:0] total_sum;
    // 3x3 window output
    reg [7:0] win_data0, win_data1, win_data2;
    reg [7:0] win_data3, win_data4, win_data5;
    reg [7:0] win_data6, win_data7, win_data8;

    reg [7:0] OFMD_in [0:63];  // 記憶體陣列形式


    reg [7:0] kernel [0:8];

    initial begin
            kernel[0] = 8'h01;  kernel[1] = 8'h02;  kernel[2] = 8'h03;
            kernel[3] = 8'h04;  kernel[4] = 8'h05;  kernel[5] = 8'h06;
            kernel[6] = 8'h07;  kernel[7] = 8'h08;  kernel[8] = 8'h09;
    end
    //convolution 
    reg [2:0] x, y;
    reg [5:0] state;

    localparam
        IDLE    = 0,
        LOAD0   = 1,  WAIT0   = 2,
        LOAD1   = 3,  WAIT1   = 4,
        LOAD2   = 5,  WAIT2   = 6,
        LOAD3   = 7,  WAIT3   = 8,
        LOAD4   = 9,  WAIT4   = 10,
        LOAD5   = 11, WAIT5   = 12,
        LOAD6   = 13, WAIT6   = 14,
        LOAD7   = 15, WAIT7   = 16,
        LOAD8   = 17, WAIT8   = 18,
        READ0   = 19, READ1   = 20,
        READ2   = 21, READ3   = 22,
        READ4   = 23, READ5   = 24,
        READ6   = 25, READ7   = 26,
        READ8   = 27,
        NEXT        = 28,
        MAC_STAGE1  = 29,
        MAC_STAGE2  = 30,
        MAC_STAGE3  = 31,
        MAC_WRITE   = 32;

    wire [5:0] win_add [0:8];
    assign win_add[0] = (y+0)*8 + (x+0);
    assign win_add[1] = (y+0)*8 + (x+1);
    assign win_add[2] = (y+0)*8 + (x+2);
    assign win_add[3] = (y+1)*8 + (x+0);
    assign win_add[4] = (y+1)*8 + (x+1);
    assign win_add[5] = (y+1)*8 + (x+2);
    assign win_add[6] = (y+2)*8 + (x+0);
    assign win_add[7] = (y+2)*8 + (x+1);
    assign win_add[8] = (y+2)*8 + (x+2);

    reg [6:0]count = 0;

    // === Initialization for state, x, y, conv_done, IFMD_addr_en, IFMD_wr_en, count ===
    initial begin
        x = 0;
        y = 0;
        state = IDLE;
        conv_done = 0;
        IFMD_read = 0;
        OFMD_addr = 0;
        count = 0;
    end

    always @(posedge clk) begin//    always @(posedge clk or posedge rst) begin
        if(conv_start) begin
            case (state)
                IDLE: begin
                    $display("Conv_IDLE");
                    if(!conv_done)begin
                        state <= LOAD0;
                        end else begin
                            $display("Conv already done");
                        end
                end

                LOAD0: begin
                    $display("Cycle %d start", y);
                    IFMD_read <= 1;
                    read_addr <= win_add[0];
                    state <= WAIT0;
                end
                WAIT0: begin
                    IFMD_read <= 0;
                    state <= READ0;
                end
                READ0: begin
                    win_data0 <= IFMD_out;
                    state <= LOAD1;
                end

                LOAD1: begin
                    IFMD_read <= 1;
                    read_addr <= win_add[1];
                    state <= WAIT1;
                end
                WAIT1: begin
                    IFMD_read <= 0;
                    state <= READ1;
                end
                READ1: begin
                    win_data1 <= IFMD_out;
                    state <= LOAD2;
                end

                LOAD2: begin
                    IFMD_read <= 1;
                    read_addr <= win_add[2];
                    state <= WAIT2;
                end
                WAIT2: begin
                    IFMD_read <= 0;
                    state <= READ2;
                end
                READ2: begin
                    win_data2 <= IFMD_out;
                    state <= LOAD3;
                end

                LOAD3: begin
                    IFMD_read <= 1;
                    read_addr <= win_add[3];
                    state <= WAIT3;
                end
                WAIT3: begin
                    IFMD_read <= 0;
                    state <= READ3;
                end
                READ3: begin
                    win_data3 <= IFMD_out;
                    state <= LOAD4;
                end

                LOAD4: begin
                    IFMD_read <= 1;
                    read_addr <= win_add[4];
                    state <= WAIT4;
                end
                WAIT4: begin
                    IFMD_read <= 0;
                    state <= READ4;
                end
                READ4: begin
                    win_data4 <= IFMD_out;
                    state <= LOAD5;
                end

                LOAD5: begin
                    IFMD_read <= 1;
                    read_addr <= win_add[5];
                    state <= WAIT5;
                end
                WAIT5: begin
                    IFMD_read <= 0;
                    state <= READ5;
                end
                READ5: begin
                    win_data5 <= IFMD_out;
                    state <= LOAD6;
                end

                LOAD6: begin
                    IFMD_read <= 1;
                    read_addr <= win_add[6];
                    state <= WAIT6;
                end
                WAIT6: begin
                    IFMD_read <= 0;
                    state <= READ6;
                end
                READ6: begin
                    win_data6 <= IFMD_out;
                    state <= LOAD7;
                end

                LOAD7: begin
                    IFMD_read <= 1;
                    read_addr <= win_add[7];
                    state <= WAIT7;
                end
                WAIT7: begin
                    IFMD_read <= 0;
                    state <= READ7;
                end
                READ7: begin
                    win_data7 <= IFMD_out;
                    state <= LOAD8;
                end

                LOAD8: begin
                    IFMD_read <= 1;
                    read_addr <= win_add[8];
                    state <= WAIT8;
                end
                WAIT8: begin
                    IFMD_read <= 0;
                    state <= READ8;
                end
                READ8: begin
                    win_data8 <= IFMD_out;
                    $display("Cycle %d done", y);
                    state <= NEXT;
                end

                NEXT: begin
                        if (x == 5) begin
                            x <= 0;
                            y <= y + 1;
                        end else begin
                            x <= x + 1;
                        end
                        state <= MAC_STAGE1;
                        
                    end
                

                MAC_STAGE1: begin
                    $display("Mac Stage 1...position%d", count);
                    mult[0] <= win_data0 * kernel[0];
                    mult[1] <= win_data1 * kernel[1];
                    mult[2] <= win_data2 * kernel[2];
                    mult[3] <= win_data3 * kernel[3];
                    mult[4] <= win_data4 * kernel[4];
                    mult[5] <= win_data5 * kernel[5];
                    mult[6] <= win_data6 * kernel[6];
                    mult[7] <= win_data7 * kernel[7];
                    mult[8] <= win_data8 * kernel[8];
                    state <= MAC_STAGE2;  
                end

                MAC_STAGE2: begin
                    sum1[0] <= mult[0] + mult[1];
                    sum1[1] <= mult[2] + mult[3];
                    sum1[2] <= mult[4] + mult[5];
                    sum1[3] <= mult[6] + mult[7];
                    mult8_reg <= mult[8];
                    state <= MAC_STAGE3;
                end

                MAC_STAGE3: begin
                    total_sum <= (sum1[0] + sum1[1]) + (sum1[2] + sum1[3]) + mult8_reg;
                    state <= MAC_WRITE;
                end
                
                MAC_WRITE: begin
                    if (count == 36) begin//x == 5 && y == 5
                        conv_done <= 1;
                        state <= IDLE;
                    end else begin
                    OFMD_addr <= count;
                    OFMD_in[count] <= total_sum;  // or OFMD_in[count] if using array
                    $display("Result[%d] = %d", count, total_sum);
                    count <= count + 1;
                    state <= LOAD0;
                    end
                end
    
            endcase
        end
    end
    // end

    wire [5:0] win_add0_dbg = win_add[0];
    wire [5:0] win_add1_dbg = win_add[1];
    wire [5:0] win_add2_dbg = win_add[2];
    wire [5:0] win_add3_dbg = win_add[3];
    wire [5:0] win_add4_dbg = win_add[4];
    wire [5:0] win_add5_dbg = win_add[5];
    wire [5:0] win_add6_dbg = win_add[6];
    wire [5:0] win_add7_dbg = win_add[7];
    wire [5:0] win_add8_dbg = win_add[8];

endmodule

read_data.v
module read_data (
    input wire clk,
    input wire write_en,
    output reg write_done,
    output reg IFMD_write,
    output reg [5:0] write_addr,
    output reg [7:0] IFMD_in
);
    reg [7:0] IFMD_data [0:63];
    reg [1:0] write_state = 0;
    reg [6:0] count;

    localparam IDLE = 0, WRITE = 1, DONE = 2;

    initial begin
        $readmemb("TM/IFMD_DATA.mem", IFMD_data);
        count <= 0;
        write_done <= 0;
        write_addr = 0;
        IFMD_in = 0;
    end

    always @(posedge clk) begin
        case (write_state)
            IDLE: begin
                if (write_en) begin
                    $display("to WRITE");
                    write_state <= WRITE;
                end
            end
            WRITE: begin
                if (count == 64) begin
                    write_done <= 1;
                    $display("write_done = %d", write_done);                    
                    $display("write_DONE!!!!!");
                    write_state <= DONE;
                end else begin
                    $display("Write_ Writing");
                    IFMD_write <= 1;
                    write_addr <= count;
                    IFMD_in <= IFMD_data[count];
                    $display("Data input... %d = %d", count, IFMD_data[write_addr]);
                    count <= count + 1;
                    write_state <= WRITE;
                end
                
                
            end
            DONE: begin    
                IFMD_write <= 0;
                write_state <= IDLE;                
            end
        endcase
    end
endmodule

fsm.v
module fsm(
    input wire clk,
    // input rst_n,
    input wire write_done,
    input wire conv_done,
    input wire start_fsm,
    output reg IFMD_write,
    output reg write_en,
    output reg conv_start,
    output reg fsm_done
);
    localparam IDLE = 2'b00, WRITE = 2'b01, CONV = 2'b10, DONE = 2'b11;
    reg [1:0] state;

    initial begin
        state = IDLE;
        IFMD_write = 0;
        conv_start = 0;
        write_en = 0;
        fsm_done = 0;
    end

    always @(posedge clk) begin
        if(start_fsm) begin
        case (state)
            IDLE: begin
                $display("FSM_Read IFMD");
                IFMD_write <= 1;
                write_en <= 1; // Enable write to IFMD RAM
                state <= WRITE;
            end
            WRITE: begin
                if (write_done) begin
                    write_en <= 0; // Disable write to IFMD RAM
                    $display("FSM_Write Done");
                    IFMD_write <= 0;
                    
                    state <= CONV;
                end else begin
                    write_en <= 1; // Keep writing to IFMD RAM
                    IFMD_write <= 1; // Keep IFMD write enabled

                    $display("FSM_WRITE");
                    state <= WRITE;
                end
            end
            CONV: begin
                if (conv_done) begin
                    state <= DONE;
                    conv_start <= 0; // Disable conv start signal
                    $display("FSM_Conv Done");
                end
                else begin
                    conv_start <= 1;
                    $display("FSM_CONV");
                    state <= CONV;
                end
            end
            DONE: begin
                state <= DONE;
                fsm_done <= 1;
                $display("FSM_Done");

            end
        endcase
        end
    end
endmodule

// module fsm(
//     input clk,
//     input in_st,
//     input IFMD_done,
//     input conv_done,
//     output reg IFMD_read,
//     output reg kernel_read,
//     output reg conv_start,
//     output reg out_st,
//     output reg [2:0] state,
//     output reg wr_in,
//     output reg wr_out
// );
//     //FSM states
//     parameter IDLE = 3'b000;
//     parameter INPUT_RAM = 3'b001;
//     parameter CONV_START = 3'b010;
//     parameter OUTPUT_RAM = 3'b011;

//     reg [2:0] current_state, next_state;

//     always @(posedge clk or negedge in_st) begin
//         if (~in_st) begin
//             current_state <= IDLE;
//         end else begin
//             current_state <= next_state;
//         end
//     end

//     always @(*) begin
//         // Initialize outputs
//         IFMD_start = 0;
//         conv_start = 0;
//         out_st = 0;
//         wr_in = 0;
//         wr_out = 1;

//         case (current_state)
//             IDLE: begin
//                 // To prevent unknown state of reading 0 memory
//                 wr_in = 1;
//                 next_state = INPUT_RAM;
//             end
//             INPUT_RAM: begin
//                 wr_in = 1;
//                 if (IFMD_done) begin
//                     next_state = CONV_START;
//                     IFMD_start = 0;
//                     conv_start = 1;
//                 end else begin
//                     next_state = INPUT_RAM;
//                     IFMD_start = 1;
//                     conv_start = 0;
//                 end
//             end
//             CONV_START: begin
//                 if (conv_done) begin
//                     next_state = OUTPUT_RAM;
//                 end else begin
//                     next_state = CONV_START;
//                 end
//             end
//             OUTPUT_RAM: begin
//                 out_st = 1; // Signal to output RAM that data is ready to be written
//                 wr_out = 1; // Enable write to output RAM
//                 next_state = IDLE; // Go back to IDLE after outputting data
//             end
//             default: begin
//                 next_state = IDLE; // Default case to handle unexpected states
//             end
//         endcase

//         state = current_state; // Update the state output
//     end
// endmodule

IFMD.v
module IFMD_ram (
    input wire clk,
    input wire IFMD_write,//=1->寫入, =0->讀出
    input wire IFMD_read,
    input wire [5:0] write_addr, //要寫入/讀出的地址
    input wire [5:0] read_addr, //啟動地址
    input wire [7:0] IFMD_in,
    output reg [7:0] IFMD_out,
    output wire [7:0] debug_mem0,
    output wire [7:0] debug_mem1,
    output wire [7:0] debug_mem2
);
    reg [7:0] IFMD_data [0:63];  
    assign debug_mem0 = IFMD_data[0];
    assign debug_mem1 = IFMD_data[1];
    assign debug_mem2 = IFMD_data[2];
    

    always @(posedge clk) begin
            if(IFMD_write)begin
                IFMD_data[write_addr] <= IFMD_in;//寫入
                $display("RAM write: addr=%0d, data=%0d", write_addr, IFMD_in);
            end            
    end
    always @(posedge clk) begin
        if(IFMD_read)begin
            IFMD_out <= IFMD_data[read_addr];//讀出
            $display("RAM read: addr=%0d, data=%0d", read_addr, IFMD_out);
        end
    end
    //end

endmodule

tb_conv.v
`timescale 1ns/1ns
`include "fsm.v"
`include "read_data.v"
`include "conv.v"

module tb_conv;
    reg clk = 0;
    wire [7:0] IFMD_in, IFMD_out;
    wire read_done, IFMD_read, IFMD_write;
    wire write_done;
    wire conv_start, conv_done;
    wire fsm_done;
    reg start_fsm;

    wire [5:0] read_addr, write_addr;
    wire write_en;

    // clock
    always #10 clk = ~clk;

    //IFMD_ram
    IFMD_ram IFMD_ram(
        .clk(clk),
        .IFMD_write(IFMD_write),            
        .IFMD_read(IFMD_read),
        .read_addr(read_addr),
        .write_addr(write_addr),
        .IFMD_in(IFMD_in),
        .IFMD_out(IFMD_out),
        .debug_mem0(),
        .debug_mem1(),
        .debug_mem2()
    );

    // FSM
    fsm fsm(
        .clk(clk),
        .start_fsm(start_fsm),
        .write_done(write_done),
        .conv_done(conv_done),
        .write_en(write_en),
        .IFMD_write(IFMD_write),
        .conv_start(conv_start),
        .fsm_done(fsm_done) 
    );

    // read_data
    read_data read_data(
        .clk(clk),
        .write_en(write_en),
        .write_done(write_done),
        .IFMD_write(IFMD_write),
        .write_addr(write_addr),
        .IFMD_in(IFMD_in)
    );

    // conv
    conv conv(
        .clk(clk),
        .conv_start(conv_start),
        .conv_done(conv_done),
        .IFMD_read(IFMD_read),
        .read_addr(read_addr),
        .IFMD_out(IFMD_out),
        //.OFMD_in(),
        .OFMD_addr()
    );

    initial begin
        $dumpfile("test.vcd");
        $dumpvars(0, tb_conv);
    end

    initial begin
        $display("=== Start Test ===");
        start_fsm = 1; 

        wait(fsm_done);
        #10;
        $display("=== Test Finished ===");
        start_fsm = 0; // Signal that the FSM is done
        $finish;
        
    end
endmodule

test.vcd
$date
	Mon Jun 16 14:43:45 2025
$end
$version
	Icarus Verilog
$end
$timescale
	1ns
$end
$scope module tb_conv $end
$var wire 1 ! IFMD_write $end
$var wire 1 " write_en $end
$var wire 1 # write_done $end
$var wire 6 $ write_addr [5:0] $end
$var wire 6 % read_addr [5:0] $end
$var wire 1 & fsm_done $end
$var wire 1 ' conv_start $end
$var wire 1 ( conv_done $end
$var wire 1 ) IFMD_read $end
$var wire 8 * IFMD_out [7:0] $end
$var wire 8 + IFMD_in [7:0] $end
$var reg 1 , clk $end
$var reg 1 - start_fsm $end
$scope module IFMD_ram $end
$var wire 1 ! IFMD_write $end
$var wire 1 , clk $end
$var wire 8 . debug_mem0 [7:0] $end
$var wire 8 / debug_mem1 [7:0] $end
$var wire 8 0 debug_mem2 [7:0] $end
$var wire 6 1 write_addr [5:0] $end
$var wire 6 2 read_addr [5:0] $end
$var wire 1 ) IFMD_read $end
$var wire 8 3 IFMD_in [7:0] $end
$var reg 8 4 IFMD_out [7:0] $end
$upscope $end
$scope module conv $end
$var wire 8 5 IFMD_out [7:0] $end
$var wire 1 , clk $end
$var wire 6 6 win_add0_dbg [5:0] $end
$var wire 6 7 win_add1_dbg [5:0] $end
$var wire 6 8 win_add2_dbg [5:0] $end
$var wire 6 9 win_add3_dbg [5:0] $end
$var wire 6 : win_add4_dbg [5:0] $end
$var wire 6 ; win_add5_dbg [5:0] $end
$var wire 6 < win_add6_dbg [5:0] $end
$var wire 6 = win_add7_dbg [5:0] $end
$var wire 6 > win_add8_dbg [5:0] $end
$var wire 1 ' conv_start $end
$var parameter 32 ? IDLE $end
$var parameter 32 @ LOAD0 $end
$var parameter 32 A LOAD1 $end
$var parameter 32 B LOAD2 $end
$var parameter 32 C LOAD3 $end
$var parameter 32 D LOAD4 $end
$var parameter 32 E LOAD5 $end
$var parameter 32 F LOAD6 $end
$var parameter 32 G LOAD7 $end
$var parameter 32 H LOAD8 $end
$var parameter 32 I MAC_STAGE1 $end
$var parameter 32 J MAC_STAGE2 $end
$var parameter 32 K MAC_STAGE3 $end
$var parameter 32 L MAC_WRITE $end
$var parameter 32 M NEXT $end
$var parameter 32 N READ0 $end
$var parameter 32 O READ1 $end
$var parameter 32 P READ2 $end
$var parameter 32 Q READ3 $end
$var parameter 32 R READ4 $end
$var parameter 32 S READ5 $end
$var parameter 32 T READ6 $end
$var parameter 32 U READ7 $end
$var parameter 32 V READ8 $end
$var parameter 32 W WAIT0 $end
$var parameter 32 X WAIT1 $end
$var parameter 32 Y WAIT2 $end
$var parameter 32 Z WAIT3 $end
$var parameter 32 [ WAIT4 $end
$var parameter 32 \ WAIT5 $end
$var parameter 32 ] WAIT6 $end
$var parameter 32 ^ WAIT7 $end
$var parameter 32 _ WAIT8 $end
$var reg 1 ) IFMD_read $end
$var reg 6 ` OFMD_addr [5:0] $end
$var reg 1 ( conv_done $end
$var reg 7 a count [6:0] $end
$var reg 14 b mult8_reg [13:0] $end
$var reg 6 c read_addr [5:0] $end
$var reg 6 d state [5:0] $end
$var reg 16 e total_sum [15:0] $end
$var reg 8 f win_data0 [7:0] $end
$var reg 8 g win_data1 [7:0] $end
$var reg 8 h win_data2 [7:0] $end
$var reg 8 i win_data3 [7:0] $end
$var reg 8 j win_data4 [7:0] $end
$var reg 8 k win_data5 [7:0] $end
$var reg 8 l win_data6 [7:0] $end
$var reg 8 m win_data7 [7:0] $end
$var reg 8 n win_data8 [7:0] $end
$var reg 3 o x [2:0] $end
$var reg 3 p y [2:0] $end
$upscope $end
$scope module fsm $end
$var wire 1 , clk $end
$var wire 1 ( conv_done $end
$var wire 1 - start_fsm $end
$var wire 1 # write_done $end
$var parameter 2 q CONV $end
$var parameter 2 r DONE $end
$var parameter 2 s IDLE $end
$var parameter 2 t WRITE $end
$var reg 1 u IFMD_write $end
$var reg 1 ' conv_start $end
$var reg 1 & fsm_done $end
$var reg 2 v state [1:0] $end
$var reg 1 " write_en $end
$upscope $end
$scope module read_data $end
$var wire 1 , clk $end
$var wire 1 " write_en $end
$var parameter 32 w DONE $end
$var parameter 32 x IDLE $end
$var parameter 32 y WRITE $end
$var reg 8 z IFMD_in [7:0] $end
$var reg 1 { IFMD_write $end
$var reg 7 | count [6:0] $end
$var reg 6 } write_addr [5:0] $end
$var reg 1 # write_done $end
$var reg 2 ~ write_state [1:0] $end
$upscope $end
$upscope $end
$enddefinitions $end
$comment Show the parameter values. $end
$dumpall
b1 y
b0 x
b10 w
b1 t
b0 s
b11 r
b10 q
b10010 _
b10000 ^
b1110 ]
b1100 \
b1010 [
b1000 Z
b110 Y
b100 X
b10 W
b11011 V
b11010 U
b11001 T
b11000 S
b10111 R
b10110 Q
b10101 P
b10100 O
b10011 N
b11100 M
b100000 L
b11111 K
b11110 J
b11101 I
b10001 H
b1111 G
b1101 F
b1011 E
b1001 D
b111 C
b101 B
b11 A
b1 @
b0 ?
$end
#0
$dumpvars
b0 ~
b0 }
b0 |
x{
b0 z
b0 v
0u
b0 p
b0 o
bx n
bx m
bx l
bx k
bx j
bx i
bx h
bx g
bx f
bx e
b0 d
bx c
bx b
b0 a
b0 `
b10010 >
b10001 =
b10000 <
b1010 ;
b1001 :
b1000 9
b10 8
b1 7
b0 6
bx 5
bx 4
b0 3
bx 2
b0 1
bx 0
bx /
bx .
1-
0,
b0 +
bx *
0)
0(
0'
0&
bx %
b0 $
0#
0"
x!
$end
#10
b1 v
1"
1u
1,
#20
0,
#30
b1 ~
1,
#40
0,
#50
b1 |
b10100110 +
b10100110 3
b10100110 z
1!
1{
1,
#60
0,
#70
b10 |
b1011100 +
b1011100 3
b1011100 z
b1 $
b1 1
b1 }
b10100110 .
1,
#80
0,
#90
b1011100 /
b11 |
b110011 +
b110011 3
b110011 z
b10 $
b10 1
b10 }
1,
#100
0,
#110
b100 |
b11110000 +
b11110000 3
b11110000 z
b11 $
b11 1
b11 }
b110011 0
1,
#120
0,
#130
b101 |
b1111 +
b1111 3
b1111 z
b100 $
b100 1
b100 }
1,
#140
0,
#150
b110 |
b10101010 +
b10101010 3
b10101010 z
b101 $
b101 1
b101 }
1,
#160
0,
#170
b111 |
b1010101 +
b1010101 3
b1010101 z
b110 $
b110 1
b110 }
1,
#180
0,
#190
b1000 |
b11000011 +
b11000011 3
b11000011 z
b111 $
b111 1
b111 }
1,
#200
0,
#210
b1001 |
b111100 +
b111100 3
b111100 z
b1000 $
b1000 1
b1000 }
1,
#220
0,
#230
b1010 |
b11111111 +
b11111111 3
b11111111 z
b1001 $
b1001 1
b1001 }
1,
#240
0,
#250
b1011 |
b0 +
b0 3
b0 z
b1010 $
b1010 1
b1010 }
1,
#260
0,
#270
b1100 |
b10011001 +
b10011001 3
b10011001 z
b1011 $
b1011 1
b1011 }
1,
#280
0,
#290
b1101 |
b1100110 +
b1100110 3
b1100110 z
b1100 $
b1100 1
b1100 }
1,
#300
0,
#310
b1110 |
b1111000 +
b1111000 3
b1111000 z
b1101 $
b1101 1
b1101 }
1,
#320
0,
#330
b1111 |
b10000111 +
b10000111 3
b10000111 z
b1110 $
b1110 1
b1110 }
1,
#340
0,
#350
b10000 |
b11001100 +
b11001100 3
b11001100 z
b1111 $
b1111 1
b1111 }
1,
#360
0,
#370
b10001 |
b110011 +
b110011 3
b110011 z
b10000 $
b10000 1
b10000 }
1,
#380
0,
#390
b10010 |
b10111100 +
b10111100 3
b10111100 z
b10001 $
b10001 1
b10001 }
1,
#400
0,
#410
b10011 |
b1000011 +
b1000011 3
b1000011 z
b10010 $
b10010 1
b10010 }
1,
#420
0,
#430
b10100 |
b11100011 +
b11100011 3
b11100011 z
b10011 $
b10011 1
b10011 }
1,
#440
0,
#450
b10101 |
b11100 +
b11100 3
b11100 z
b10100 $
b10100 1
b10100 }
1,
#460
0,
#470
b10110 |
b11011011 +
b11011011 3
b11011011 z
b10101 $
b10101 1
b10101 }
1,
#480
0,
#490
b10111 |
b100100 +
b100100 3
b100100 z
b10110 $
b10110 1
b10110 }
1,
#500
0,
#510
b11000 |
b11111100 +
b11111100 3
b11111100 z
b10111 $
b10111 1
b10111 }
1,
#520
0,
#530
b11001 |
b11 +
b11 3
b11 z
b11000 $
b11000 1
b11000 }
1,
#540
0,
#550
b11010 |
b10000001 +
b10000001 3
b10000001 z
b11001 $
b11001 1
b11001 }
1,
#560
0,
#570
b11011 |
b1111110 +
b1111110 3
b1111110 z
b11010 $
b11010 1
b11010 }
1,
#580
0,
#590
b11100 |
b10000000 +
b10000000 3
b10000000 z
b11011 $
b11011 1
b11011 }
1,
#600
0,
#610
b11101 |
b1 +
b1 3
b1 z
b11100 $
b11100 1
b11100 }
1,
#620
0,
#630
b11110 |
b11111110 +
b11111110 3
b11111110 z
b11101 $
b11101 1
b11101 }
1,
#640
0,
#650
b11111 |
b10101001 +
b10101001 3
b10101001 z
b11110 $
b11110 1
b11110 }
1,
#660
0,
#670
b100000 |
b1010110 +
b1010110 3
b1010110 z
b11111 $
b11111 1
b11111 }
1,
#680
0,
#690
b100001 |
b101010 +
b101010 3
b101010 z
b100000 $
b100000 1
b100000 }
1,
#700
0,
#710
b100010 |
b11010101 +
b11010101 3
b11010101 z
b100001 $
b100001 1
b100001 }
1,
#720
0,
#730
b100011 |
b10110011 +
b10110011 3
b10110011 z
b100010 $
b100010 1
b100010 }
1,
#740
0,
#750
b100100 |
b1001100 +
b1001100 3
b1001100 z
b100011 $
b100011 1
b100011 }
1,
#760
0,
#770
b100101 |
b10011000 +
b10011000 3
b10011000 z
b100100 $
b100100 1
b100100 }
1,
#780
0,
#790
b100110 |
b1100111 +
b1100111 3
b1100111 z
b100101 $
b100101 1
b100101 }
1,
#800
0,
#810
b100111 |
b11111100 +
b11111100 3
b11111100 z
b100110 $
b100110 1
b100110 }
1,
#820
0,
#830
b101000 |
b11 +
b11 3
b11 z
b100111 $
b100111 1
b100111 }
1,
#840
0,
#850
b101001 |
b10110110 +
b10110110 3
b10110110 z
b101000 $
b101000 1
b101000 }
1,
#860
0,
#870
b101010 |
b1001001 +
b1001001 3
b1001001 z
b101001 $
b101001 1
b101001 }
1,
#880
0,
#890
b101011 |
b11001111 +
b11001111 3
b11001111 z
b101010 $
b101010 1
b101010 }
1,
#900
0,
#910
b101100 |
b110000 +
b110000 3
b110000 z
b101011 $
b101011 1
b101011 }
1,
#920
0,
#930
b101101 |
b11110001 +
b11110001 3
b11110001 z
b101100 $
b101100 1
b101100 }
1,
#940
0,
#950
b101110 |
b1110 +
b1110 3
b1110 z
b101101 $
b101101 1
b101101 }
1,
#960
0,
#970
b101111 |
b10101111 +
b10101111 3
b10101111 z
b101110 $
b101110 1
b101110 }
1,
#980
0,
#990
b110000 |
b1010000 +
b1010000 3
b1010000 z
b101111 $
b101111 1
b101111 }
1,
#1000
0,
#1010
b110001 |
b11100000 +
b11100000 3
b11100000 z
b110000 $
b110000 1
b110000 }
1,
#1020
0,
#1030
b110010 |
b11111 +
b11111 3
b11111 z
b110001 $
b110001 1
b110001 }
1,
#1040
0,
#1050
b110011 |
b10010010 +
b10010010 3
b10010010 z
b110010 $
b110010 1
b110010 }
1,
#1060
0,
#1070
b110100 |
b1101101 +
b1101101 3
b1101101 z
b110011 $
b110011 1
b110011 }
1,
#1080
0,
#1090
b110101 |
b11000000 +
b11000000 3
b11000000 z
b110100 $
b110100 1
b110100 }
1,
#1100
0,
#1110
b110110 |
b111111 +
b111111 3
b111111 z
b110101 $
b110101 1
b110101 }
1,
#1120
0,
#1130
b110111 |
b10011100 +
b10011100 3
b10011100 z
b110110 $
b110110 1
b110110 }
1,
#1140
0,
#1150
b111000 |
b1100011 +
b1100011 3
b1100011 z
b110111 $
b110111 1
b110111 }
1,
#1160
0,
#1170
b111001 |
b11101110 +
b11101110 3
b11101110 z
b111000 $
b111000 1
b111000 }
1,
#1180
0,
#1190
b111010 |
b10001 +
b10001 3
b10001 z
b111001 $
b111001 1
b111001 }
1,
#1200
0,
#1210
b111011 |
b10111010 +
b10111010 3
b10111010 z
b111010 $
b111010 1
b111010 }
1,
#1220
0,
#1230
b111100 |
b1000101 +
b1000101 3
b1000101 z
b111011 $
b111011 1
b111011 }
1,
#1240
0,
#1250
b111101 |
b11010110 +
b11010110 3
b11010110 z
b111100 $
b111100 1
b111100 }
1,
#1260
0,
#1270
b111110 |
b101001 +
b101001 3
b101001 z
b111101 $
b111101 1
b111101 }
1,
#1280
0,
#1290
b111111 |
b11111000 +
b11111000 3
b11111000 z
b111110 $
b111110 1
b111110 }
1,
#1300
0,
#1310
b1000000 |
b111 +
b111 3
b111 z
b111111 $
b111111 1
b111111 }
1,
#1320
0,
#1330
b10 ~
1#
1,
#1340
0,
#1350
b0 ~
0{
b10 v
0!
0u
0"
1,
#1360
0,
#1370
1'
1,
#1380
0,
#1390
b1 d
1,
#1400
0,
#1410
b10 d
b0 %
b0 2
b0 c
1)
1,
#1420
0,
#1430
b10011 d
0)
b10100110 *
b10100110 4
b10100110 5
1,
#1440
0,
#1450
b11 d
b10100110 f
1,
#1460
0,
#1470
b100 d
b1 %
b1 2
b1 c
1)
1,
#1480
0,
#1490
b1011100 *
b1011100 4
b1011100 5
b10100 d
0)
1,
#1500
0,
#1510
b101 d
b1011100 g
1,
#1520
0,
#1530
b110 d
b10 %
b10 2
b10 c
1)
1,
#1540
0,
#1550
b10101 d
0)
b110011 *
b110011 4
b110011 5
1,
#1560
0,
#1570
b111 d
b110011 h
1,
#1580
0,
#1590
b1000 d
b1000 %
b1000 2
b1000 c
1)
1,
#1600
0,
#1610
b111100 *
b111100 4
b111100 5
b10110 d
0)
1,
#1620
0,
#1630
b1001 d
b111100 i
1,
#1640
0,
#1650
b1010 d
b1001 %
b1001 2
b1001 c
1)
1,
#1660
0,
#1670
b10111 d
0)
b11111111 *
b11111111 4
b11111111 5
1,
#1680
0,
#1690
b1011 d
b11111111 j
1,
#1700
0,
#1710
b1100 d
b1010 %
b1010 2
b1010 c
1)
1,
#1720
0,
#1730
b0 *
b0 4
b0 5
b11000 d
0)
1,
#1740
0,
#1750
b1101 d
b0 k
1,
#1760
0,
#1770
b1110 d
b10000 %
b10000 2
b10000 c
1)
1,
#1780
0,
#1790
b11001 d
0)
b110011 *
b110011 4
b110011 5
1,
#1800
0,
#1810
b1111 d
b110011 l
1,
#1820
0,
#1830
b10000 d
b10001 %
b10001 2
b10001 c
1)
1,
#1840
0,
#1850
b10111100 *
b10111100 4
b10111100 5
b11010 d
0)
1,
#1860
0,
#1870
b10001 d
b10111100 m
1,
#1880
0,
#1890
b10010 d
b10010 %
b10010 2
b10010 c
1)
1,
#1900
0,
#1910
b11011 d
0)
b1000011 *
b1000011 4
b1000011 5
1,
#1920
0,
#1930
b11100 d
b1000011 n
1,
#1940
0,
#1950
b11101 d
b1 6
b10 7
b11 8
b1001 9
b1010 :
b1011 ;
b10001 <
b10010 =
b10011 >
b1 o
1,
#1960
0,
#1970
b11110 d
1,
#1980
0,
#1990
b11111 d
b1001011011 b
1,
#2000
0,
#2010
b100000 d
b1000110000010 e
1,
#2020
0,
#2030
b1 d
b1 a
1,
#2040
0,
#2050
b10 d
b1 %
b1 2
b1 c
1)
1,
#2060
0,
#2070
b10011 d
0)
b1011100 *
b1011100 4
b1011100 5
1,
#2080
0,
#2090
b11 d
b1011100 f
1,
#2100
0,
#2110
b100 d
b10 %
b10 2
b10 c
1)
1,
#2120
0,
#2130
b110011 *
b110011 4
b110011 5
b10100 d
0)
1,
#2140
0,
#2150
b101 d
b110011 g
1,
#2160
0,
#2170
b110 d
b11 %
b11 2
b11 c
1)
1,
#2180
0,
#2190
b10101 d
0)
b11110000 *
b11110000 4
b11110000 5
1,
#2200
0,
#2210
b111 d
b11110000 h
1,
#2220
0,
#2230
b1000 d
b1001 %
b1001 2
b1001 c
1)
1,
#2240
0,
#2250
b11111111 *
b11111111 4
b11111111 5
b10110 d
0)
1,
#2260
0,
